odoo8_addon_product_rating-8.0.1.0.0.99.dev3-py3.8-nspkg.pth
odoo_addons/product_rating/README.rst
odoo_addons/product_rating/__init__.py
odoo_addons/product_rating/__openerp__.py
odoo_addons/product_rating/data/product_rating_data.xml
odoo_addons/product_rating/models/__init__.py
odoo_addons/product_rating/models/product.py
odoo_addons/product_rating/models/product_rating.py
odoo_addons/product_rating/security/ir.model.access.csv
odoo_addons/product_rating/views/product_rating_view.xml
odoo_addons/product_rating/views/product_view.xml
odoo8_addon_product_rating-8.0.1.0.0.99.dev3.dist-info/METADATA
odoo8_addon_product_rating-8.0.1.0.0.99.dev3.dist-info/WHEEL
odoo8_addon_product_rating-8.0.1.0.0.99.dev3.dist-info/namespace_packages.txt
odoo8_addon_product_rating-8.0.1.0.0.99.dev3.dist-info/top_level.txt
odoo8_addon_product_rating-8.0.1.0.0.99.dev3.dist-info/RECORD
