Metadata-Version: 2.1
Name: odoo8-addon-product-rating
Version: 8.0.1.0.0.99.dev3
Summary: Rate your product
Home-page: http://www.akretion.com/fr
Author: Akretion
License: AGPL-3
Platform: UNKNOWN
Classifier: Programming Language :: Python
Classifier: Framework :: Odoo
Classifier: License :: OSI Approved :: GNU Affero General Public License v3
Requires-Python: ~=2.7
Requires-Dist: odoo (<9.0a,>=8.0a)
